auto_round/__init__.py
auto_round/__main__.py
auto_round/alg_ext.py
auto_round/autoround.py
auto_round/calib_dataset.py
auto_round/envs.py
auto_round/formats.py
auto_round/logger.py
auto_round/schemes.py
auto_round/sign_sgd.py
auto_round/special_model_handler.py
auto_round/testing_utils.py
auto_round/version.py
auto_round/wrapper.py
auto_round/auto_scheme/__init__.py
auto_round/auto_scheme/delta_loss.py
auto_round/auto_scheme/gen_auto_scheme.py
auto_round/auto_scheme/register.py
auto_round/auto_scheme/utils.py
auto_round/compressors/__init__.py
auto_round/compressors/adam.py
auto_round/compressors/base.py
auto_round/compressors/config.py
auto_round/compressors/shard_writer.py
auto_round/compressors/utils.py
auto_round/compressors/diffusion/__init__.py
auto_round/compressors/diffusion/compressor.py
auto_round/compressors/diffusion/dataset.py
auto_round/compressors/diffusion/eval.py
auto_round/compressors/mllm/__init__.py
auto_round/compressors/mllm/compressor.py
auto_round/compressors/mllm/dataset.py
auto_round/compressors/mllm/eval.py
auto_round/compressors/mllm/processor.py
auto_round/compressors/mllm/template.py
auto_round/compressors/mllm/utils.py
auto_round/compressors/mllm/templates/cogvlm2.json
auto_round/compressors/mllm/templates/default.json
auto_round/compressors/mllm/templates/llava.json
auto_round/compressors/mllm/templates/phi3_v.json
auto_round/data_type/__init__.py
auto_round/data_type/fp8.py
auto_round/data_type/gguf.py
auto_round/data_type/int.py
auto_round/data_type/mxfp.py
auto_round/data_type/nvfp.py
auto_round/data_type/register.py
auto_round/data_type/utils.py
auto_round/data_type/w4fp8.py
auto_round/eval/__init__.py
auto_round/eval/eval_cli.py
auto_round/eval/evaluation.py
auto_round/experimental/__init__.py
auto_round/experimental/attention.py
auto_round/experimental/kv_cache.py
auto_round/experimental/utils.py
auto_round/experimental/qmodules/__init__.py
auto_round/experimental/qmodules/base.py
auto_round/experimental/qmodules/fp4_utils.py
auto_round_nightly-0.10.0.dev20260131.dist-info/licenses/LICENSE
auto_round_nightly-0.10.0.dev20260131.dist-info/licenses/third-party-programs.txt
auto_round_nightly-0.10.0.dev20260131.dist-info/METADATA
auto_round_nightly-0.10.0.dev20260131.dist-info/WHEEL
auto_round_nightly-0.10.0.dev20260131.dist-info/entry_points.txt
auto_round_nightly-0.10.0.dev20260131.dist-info/top_level.txt
auto_round_nightly-0.10.0.dev20260131.dist-info/RECORD
