Metadata-Version: 2.4
Name: auto-round-nightly
Version: 0.10.0.dev20260131
Summary: Repository of AutoRound: Advanced Weight-Only Quantization Algorithm for LLMs
Home-page: https://github.com/intel/auto-round
Author: Intel AIPT Team
Author-email: wenhua.cheng@intel.com, weiwei1.zhang@intel.com, heng.guo@intel.com
License: Apache 2.0
Keywords: quantization,auto-around,LLM,SignRound
Classifier: Intended Audience :: Science/Research
Classifier: Programming Language :: Python :: 3
Classifier: Topic :: Scientific/Engineering :: Artificial Intelligence
Classifier: License :: OSI Approved :: Apache Software License
Requires-Python: >=3.10.0
License-File: LICENSE
License-File: third-party-programs.txt
Requires-Dist: accelerate
Requires-Dist: datasets
Requires-Dist: numpy
Requires-Dist: py-cpuinfo
Requires-Dist: threadpoolctl
Requires-Dist: torch
Requires-Dist: tqdm
Requires-Dist: transformers>=4.38
Provides-Extra: cpu
Requires-Dist: numba; extra == "cpu"
Requires-Dist: tbb; extra == "cpu"
Requires-Dist: intel-extension-for-pytorch; extra == "cpu"
Dynamic: author
Dynamic: author-email
Dynamic: classifier
Dynamic: description
Dynamic: description-content-type
Dynamic: home-page
Dynamic: keywords
Dynamic: license
Dynamic: license-file
Dynamic: provides-extra
Dynamic: requires-dist
Dynamic: requires-python
Dynamic: summary
